databda/__init__.py
databda/data.py
databda/main.py
databda-0.1.0.dist-info/LICENSE
databda-0.1.0.dist-info/METADATA
databda-0.1.0.dist-info/WHEEL
databda-0.1.0.dist-info/top_level.txt
databda-0.1.0.dist-info/RECORD
