Metadata-Version: 2.1
Name: databda
Version: 0.1.0
Summary: A program for local 'hashing' of data
Author-email: Andrey <dorofeevav1149@gmail.com>
Project-URL: Homepage, https://turnmanedition.github.io/IsTericad.com/
Project-URL: Issues, https://github.com/TurnManEDITION/IsTericad.com
Classifier: Programming Language :: Python :: 3
Classifier: License :: OSI Approved :: MIT License
Classifier: Operating System :: OS Independent
Requires-Python: >=3.8
License-File: LICENSE
